channels_jsonrpc/__init__.py
channels_jsonrpc/jsonrpcwebsocketconsumer.py
django_channels_jsonrpc-1.0.0.dist-info/DESCRIPTION.rst
django_channels_jsonrpc-1.0.0.dist-info/METADATA
django_channels_jsonrpc-1.0.0.dist-info/RECORD
django_channels_jsonrpc-1.0.0.dist-info/WHEEL
django_channels_jsonrpc-1.0.0.dist-info/metadata.json
django_channels_jsonrpc-1.0.0.dist-info/top_level.txt
